authentication/__init__.py
authentication/admin.py
authentication/apps.py
authentication/tests.py
authentication/urls.py
authentication/views.py
authentication/migrations/0001_initial.py
authentication/migrations/__init__.py
authentication/models/__init__.py
authentication/models/managers.py
authentication/models/users.py
authentication/utils/__init__.py
authentication/utils/token.py
user_authentication_jr-0.0.10.dist-info/LICENSE
user_authentication_jr-0.0.10.dist-info/METADATA
user_authentication_jr-0.0.10.dist-info/WHEEL
user_authentication_jr-0.0.10.dist-info/top_level.txt
user_authentication_jr-0.0.10.dist-info/RECORD
