Metadata-Version: 2.1
Name: user-authentication-jr
Version: 0.0.10
Summary: A django app with token based authentication for both Session and API Token
Home-page: https://github.com/jrbenriquez/user-authentication-jr
Author: John Rei Enriquez
Author-email: johnrei.enriquez@gmail.com
License: UNKNOWN
Platform: UNKNOWN
Classifier: Programming Language :: Python :: 3
Classifier: License :: OSI Approved :: MIT License
Classifier: Operating System :: OS Independent
Requires-Python: >=3.6
Requires-Dist: django-cors-headers (==3.3.0)
Requires-Dist: django-rest-framework (==0.1.0)
Requires-Dist: djangorestframework (==3.11.0)
